LICENSE
README.md
hardbrake
requirements.txt
setup.py
hardbrake.egg-info/PKG-INFO
hardbrake.egg-info/SOURCES.txt
hardbrake.egg-info/dependency_links.txt
hardbrake.egg-info/requires.txt
hardbrake.egg-info/top_level.txt
src/__init__.py
src/app.py
src/config.py
src/event.py
src/file.py
src/loader.py
src/logger.py
src/manager.py
src/prompts.py
src/utils.py