Metadata-Version: 2.1
Name: hardbrake
Version: 0.2.0
Summary: A wrapper around HandBrake CLI for encoding multiple files with ease.
Author: Tahsin
Author-email: hello@tahsin.us
License-File: LICENSE
